{
  "codebase_version": "v2.1",
  "robot_type": "franka_panda",
  "total_episodes": 2,
  "total_frames": 2741,
  "total_tasks": 1,
  "total_videos": 4,
  "fps": 60,
  "splits": {
    "train": "0:2"
  },
  "features": {
    "observation.state": {
      "dtype": "float32",
      "shape": [
        37
      ],
      "names": [
        "joint_0",
        "joint_1",
        "joint_2",
        "joint_3",
        "joint_4",
        "joint_5",
        "joint_6",
        "joint_7",
        "joint_8",
        "joint_9",
        "joint_10",
        "joint_11",
        "joint_12",
        "joint_13",
        "joint_14",
        "joint_15",
        "joint_16",
        "joint_17",
        "joint_18",
        "joint_19",
        "joint_20",
        "joint_21",
        "joint_22",
        "joint_23",
        "joint_24",
        "joint_25",
        "joint_26",
        "joint_27",
        "joint_28",
        "joint_29",
        "joint_30",
        "joint_31",
        "joint_32",
        "joint_33",
        "joint_34",
        "joint_35",
        "joint_36"
      ]
    },
    "action": {
      "dtype": "float32",
      "shape": [
        7
      ],
      "names": [
        "action_0",
        "action_1",
        "action_2",
        "action_3",
        "action_4",
        "action_5",
        "action_6"
      ]
    },
    "timestamp": {
      "dtype": "float64",
      "shape": [],
      "names": null
    },
    "episode_index": {
      "dtype": "int64",
      "shape": [],
      "names": null
    },
    "frame_index": {
      "dtype": "int64",
      "shape": [],
      "names": null
    },
    "index": {
      "dtype": "int64",
      "shape": [],
      "names": null
    },
    "task_index": {
      "dtype": "int64",
      "shape": [],
      "names": null
    },
    "observation.images.r1_main_cam": {
      "dtype": "video",
      "shape": [
        224,
        224,
        3
      ],
      "names": [
        "height",
        "width",
        "channel"
      ],
      "info": {
        "video.fps": 30,
        "video.codec": "mp4v",
        "video.pix_fmt": "yuv420p",
        "video.is_depth_map": false,
        "has_audio": false
      }
    },
    "observation.images.r1_wrist_cam": {
      "dtype": "video",
      "shape": [
        224,
        224,
        3
      ],
      "names": [
        "height",
        "width",
        "channel"
      ],
      "info": {
        "video.fps": 30,
        "video.codec": "mp4v",
        "video.pix_fmt": "yuv420p",
        "video.is_depth_map": false,
        "has_audio": false
      }
    }
  }
}